pytest_mock_helper.py
pytest_mock_helper-0.2.1.dist-info/DESCRIPTION.rst
pytest_mock_helper-0.2.1.dist-info/METADATA
pytest_mock_helper-0.2.1.dist-info/RECORD
pytest_mock_helper-0.2.1.dist-info/WHEEL
pytest_mock_helper-0.2.1.dist-info/entry_points.txt
pytest_mock_helper-0.2.1.dist-info/metadata.json
pytest_mock_helper-0.2.1.dist-info/top_level.txt
